lanzou/__init__.py
lanzou/api/__init__.py
lanzou/api/core.py
lanzou/api/models.py
lanzou/api/types.py
lanzou/api/utils.py
lanzou_api-2.6.10.dist-info/LICENSE
lanzou_api-2.6.10.dist-info/METADATA
lanzou_api-2.6.10.dist-info/WHEEL
lanzou_api-2.6.10.dist-info/top_level.txt
lanzou_api-2.6.10.dist-info/RECORD
