Metadata-Version: 2.1
Name: lanzou-api
Version: 2.6.10
Summary: LanZouCloud API
Home-page: https://github.com/zaxtyson/LanZouCloud-API
Author: zaxtyson
Author-email: zaxtyson@foxmail.com
License: UNKNOWN
Platform: UNKNOWN
Classifier: Programming Language :: Python :: 3
Classifier: Operating System :: OS Independent
Requires-Dist: requests
Requires-Dist: requests-toolbelt
